nanowakeword/__init__.py
nanowakeword/analyzer.py
nanowakeword/architectures.py
nanowakeword/config_generator.py
nanowakeword/data.py
nanowakeword/generate_samples.py
nanowakeword/nanointerpreter.py
nanowakeword/trainer.py
nanowakeword/vad.py
nanowakeword/data_utils/__init__.py
nanowakeword/data_utils/preprocess.py
nanowakeword/resources/__init__.py
nanowakeword/resources/models/__init__.py
nanowakeword/resources/models/_registry.py
nanowakeword/utils/__init__.py
nanowakeword/utils/audio_processing.py
nanowakeword/utils/download_file.py
nanowakeword/utils/logger.py
nanowakeword-1.3.3.dist-info/licenses/LICENSE
nanowakeword-1.3.3.dist-info/METADATA
nanowakeword-1.3.3.dist-info/WHEEL
nanowakeword-1.3.3.dist-info/entry_points.txt
nanowakeword-1.3.3.dist-info/top_level.txt
nanowakeword-1.3.3.dist-info/RECORD
