Metadata-Version: 2.4
Name: nanowakeword
Version: 1.3.3
Summary: A next-generation intelligent framework for efficiently training high-performance, custom wake word models.
Author-email: Arcosoph <a5tkabid@gmail.com>
License-Expression: Apache-2.0
Project-URL: Homepage, https://github.com/arcosoph/nanowakeword
Project-URL: Bug Tracker, https://github.com/arcosoph/nanowakeword/issues
Keywords: wakeword,keyword-spotting,pytorch,kws,speech-recognition,nanowakeword
Classifier: Development Status :: 4 - Beta
Classifier: Intended Audience :: Developers
Classifier: Operating System :: OS Independent
Classifier: Programming Language :: Python :: 3
Classifier: Programming Language :: Python :: 3.8
Classifier: Programming Language :: Python :: 3.9
Classifier: Programming Language :: Python :: 3.10
Classifier: Programming Language :: Python :: 3.11
Classifier: Programming Language :: Python :: 3.12
Classifier: Programming Language :: Python :: 3.13
Classifier: Topic :: Scientific/Engineering :: Artificial Intelligence
Classifier: Topic :: Software Development :: Libraries :: Python Modules
Requires-Python: >=3.8
License-File: LICENSE
Requires-Dist: numpy<3.0,>=2.0
Requires-Dist: onnxruntime<2.0,>=1.15
Provides-Extra: train
Requires-Dist: torch<2.9,>=2.8; extra == "train"
Requires-Dist: torchaudio<2.9,>=2.8; extra == "train"
Requires-Dist: scipy<2.0,>=1.11; extra == "train"
Requires-Dist: scikit-learn<2.0,>=1.3; extra == "train"
Requires-Dist: onnx<2.0,>=1.14; extra == "train"
Requires-Dist: acoustics<0.3,>=0.2.3; extra == "train"
Requires-Dist: librosa<1.0,>=0.10; extra == "train"
Requires-Dist: pydub<1.0,>=0.25; extra == "train"
Requires-Dist: audiomentations<1.0,>=0.30; extra == "train"
Requires-Dist: torch_audiomentations<1.0,>=0.11; extra == "train"
Requires-Dist: soundfile<1.0,>=0.12; extra == "train"
Requires-Dist: mutagen<2.0,>=1.46; extra == "train"
Requires-Dist: phonemize<1.0,>=0.2; extra == "train"
Requires-Dist: pronouncing<1.0,>=0.2; extra == "train"
Requires-Dist: sounddevice<1.0,>=0.4.6; extra == "train"
Requires-Dist: PyYAML<7.0,>=6.0; extra == "train"
Requires-Dist: rich<14.0,>=13.0; extra == "train"
Requires-Dist: tqdm<5.0,>=4.64; extra == "train"
Requires-Dist: matplotlib<4.0,>=3.7; extra == "train"
Requires-Dist: torchinfo<2.0,>=1.8; extra == "train"
Requires-Dist: torchmetrics<2.0,>=1.3; extra == "train"
Requires-Dist: psutil; extra == "train"
Requires-Dist: requests<3.0,>=2.28; extra == "train"
Dynamic: license-file
